LICENSE
MANIFEST.in
README.md
setup.cfg
setup.py
tangent/__init__.py
tangent/anf.py
tangent/annotate.py
tangent/annotations.py
tangent/ast.py
tangent/cfg.py
tangent/comments.py
tangent/compile.py
tangent/create.py
tangent/errors.py
tangent/fence.py
tangent/fixes.py
tangent/forward_ad.py
tangent/funcsigs.py
tangent/grad_util.py
tangent/grads.py
tangent/grammar.py
tangent/naming.py
tangent/non_differentiable.py
tangent/optimization.py
tangent/quoting.py
tangent/reverse_ad.py
tangent/tangents.py
tangent/template.py
tangent/tf_extensions.py
tangent/tracing.py
tangent/transformers.py
tangent/utils.py
tangent.egg-info/PKG-INFO
tangent.egg-info/SOURCES.txt
tangent.egg-info/dependency_links.txt
tangent.egg-info/requires.txt
tangent.egg-info/top_level.txt