Metadata-Version: 1.0
Name: tangent
Version: 0.1.8
Summary: Automatic differentiation using source code transformation for Python
Home-page: https://github.com/google/tangent
Author: Google Inc.
Author-email: alexbw@google.com
License: 
